zogutils/__init__.py
zogutils/middlewares/__init__.py
zogutils/middlewares/exceptions.py
zogutils/middlewares/logger.py
zogutils/middlewares/monitoring.py
zogutils/middlewares/securities.py
zogutils/package_name.py
zogutils/secret.py
zogutils-1.5.1.dist-info/WHEEL
zogutils-1.5.1.dist-info/METADATA
zogutils-1.5.1.dist-info/RECORD
