Metadata-Version: 2.1
Name: zogutils
Version: 1.5.1
Summary: General utilities to be use in my base-fastapi template. Why ZOG? It's sound like joke and look like zoo.
Home-page: https://github.com/tienhm0202/zogutils
Author: Hoang Manh Tien
Author-email: tienhm.0202@gmail.com
Requires-Python: >=3.7.0,<3.8.0
Classifier: Programming Language :: Python :: 3
Classifier: Programming Language :: Python :: 3.7
Requires-Dist: fastapi (==0.61.1)
Requires-Dist: googletrans (>=3.0.0,<4.0.0)
Requires-Dist: piccolo-api (>=0.11.1,<0.12.0)
Requires-Dist: sentry-sdk (==0.19.0)
Requires-Dist: starlette-prometheus (==0.7.0)
Project-URL: Repository, https://github.com/tienhm0202/zogutils
